Workbook

Sheet README
A1: BSS Math Sheet — Starter Template
A3: Purpose
A4: Live Math + 3-Neighborhood Shortlist for the Orlando First-Time Buyer Buyer Strategy Session. Duplicate this workbook once per prospect at booking time, then drive it from the Inputs tab live during the call.
A6: Tabs (in run order)
A7: 1. Inputs — All agent-typed values. Yellow cells = type here. Cells B2-B14 follow the spec exactly.
A8: 2. PITI Build-Up — Property tax (new-owner basis with homestead), HO3 insurance, HOA. Source of truth for tax/ins.
A9: 3. Loan Scenarios — Three loan paths side by side: FHA 3.5%, Conv 5%, Conv 20%. P&I, MI on its own line, total PITI, DTI.
A10: 4. Cash to Close — Down + line-item closing costs + BAC row (editable, default $0 = seller-paid).
A11: 5. Reserves After Close — Reserves $ and months. Yellow/red flags for both reserves and back-end DTI.
A12: 6. Shortlist Math — 3 ZIP comparison (plus optional 4th). One scenario applied across all ZIPs; toggle in cell D3.
A14: Color conventions
A15: • Blue text on yellow fill = INPUT cells (type here).
... A37: CLAUDE.md — funnel-wide hard rules and market context.

Sheet Inputs
A1: BSS Math Sheet — Inputs | C1: Type into the yellow cells. Everything downstream recalculates automatically.
A2: First name | B2: Maria | C2: Per LM1 intake.
A3: Co-buyer? | B3: No | C3: 'Yes' or 'No'. If yes, combine incomes/debts in rows 4-5.
A4: Combined gross income, monthly | B4: 7800 | C4: Both buyers combined. Gross (pre-tax).
A5: Existing monthly debts (cars, students, minimums) | B5: 620 | C5: Anything that hits a credit report each month.
A6: Credit band (per LM1 Q1) | B6: 680-739 | C6: 740+, 680-739, 620-679, <620, unknown.
A7: Cash available for the deal | B7: 32000 | C7: Total liquid cash earmarked for this purchase.
A8: Target purchase price (starting guess) | B8: 360000 | C8: Adjust live during the call as the math evolves.
A9: Term (years) | B9: 30 | C9: Almost always 30. 15 only if prospect raises it.
A10: Property type | B10: SFH (2000s or newer) | C10: SFH (newer), SFH (older), Townhome, Condo. Drives insurance band.
A11: County | B11: Seminole | C11: 'Seminole' or 'Orange'. Drives millage rate.
A12: Estimated HOA, monthly | B12: 0 | C12: $0 for most SFH; enter representative value the prospect can override.
A13: Expected rate today | B13: 0.06875 | C13: Today's quote from the 3-lender card. Refresh day of call.
A14: Neighborhoods prospect named (free text) | B14: Sanford, maybe Lake Mary | C14: Drives Shortlist Math tab (Path A / B / C decision).
A16: CALIBRATION & ASSUMPTIONS — update from current sources quarterly
A17: FHA down payment % | B17: 0.035 | C17: Statutory FHA minimum.
A18: FHA upfront MIP % (financed into loan) | B18: 0.0175 | C18: Verify against HUD handbook 4000.1 before each call.
A19: FHA annual MIP % | B19: 0.0055 | C19: Verify against HUD handbook 4000.1.
A20: Conventional low-down % | B20: 0.05 | C20: Conv 95% LTV. Switch to 0.03 for HomeReady/Home Possible if relevant.
A21: Conventional PMI % (annual, of loan) | B21: 0.006 | C21: Calibrate to credit band. Replace with real lender quote.
A22: Conventional full-down % | B22: 0.2 | C22: 20% = no PMI.
A23: Florida homestead exemption ($) | B23: 50000 | C23: Primary residence only.
A24: Seminole County millage (effective) | B24: 0.0145 | C24: Higher inside city limits.
A25: Orange County millage (effective) | B25: 0.0135 | C25: Downtown Orlando city add-on.
A26: Annual HO3 insurance estimate ($) | B26: 3300 | C26: Refresh quarterly with broker. Add flood if AE/VE zone.
A27: Closing — lender fees (origination, underwriting, processing) | B27: 2000 | C27: Range $1,500-$2,500. Negotiable.
A28: Closing — title (owner + lender policy + settlement) | B28: 2750 | C28: Range $2,000-$3,500.
... A37: Back-end DTI RED threshold | B37: 0.5 | C37: FHA may tolerate up to ~57% in some cases.

Sheet PITI Build-Up
A1: PITI Build-Up | C1: Tax, insurance, HOA build — pulled by formula into Loan Scenarios.
A3: PROPERTY TAX (Florida, new-owner basis)
A4: Purchase price | B4: =Inputs!B8 -> 360000 | C4: Pulled from Inputs!B8.
A5: County | B5: =Inputs!B11 -> Seminole | C5: Pulled from Inputs!B11.
A6: Homestead exemption | B6: =Inputs!B23 -> 50000 | C6: Pulled from Inputs!B23.
A7: Year-1 assessed value (= purchase price; Save-Our-Homes resets on sale) | B7: =B4 -> 360000 | C7: Quote the new-owner number, NOT the seller's last tax bill.
A8: Millage rate applied | B8: =IF(B5="Seminole",Inputs!B24,IF(B5="Orange",Inputs!B25,0)) -> 0.0145 | C8: Auto-pick by county. Defaults to 0 if county not recognized.
A9: Annual property tax (new-owner) | B9: =MAX(0,B7-B6)*B8 -> 4495 | C9: = MAX(0, assessed - homestead) * millage.
A10: Monthly property tax | B10: =B9/12 -> 374.58333 | C10: Used by Loan Scenarios.
A12: HOMEOWNERS INSURANCE (FL HO3 / HO6)
A13: Annual HO3/HO6 estimate | B13: =Inputs!B26 -> 3300 | C13: Pulled from Inputs!B26. Refresh band per property profile.
A14: Monthly insurance | B14: =B13/12 -> 275 | C14: Used by Loan Scenarios.
A16: HOA
A17: Monthly HOA | B17: =Inputs!B12 -> 0 | C17: Pulled from Inputs!B12. Used by Loan Scenarios.

Sheet Loan Scenarios
A1: Loan Scenarios | C1: Three loan paths side by side — same price, same rate, same prospect.
A3: Line item | B3: FHA 3.5% down | C3: Conventional 5% down | D3: Conventional 20% down
A4: Down payment % | B4: =Inputs!B17 -> 0.035 | C4: =Inputs!B20 -> 0.05 | D4: =Inputs!B22 -> 0.2
A5: Down payment $ | B5: =Inputs!B8*B4 -> 12600 | C5: =Inputs!B8*C4 -> 18000 | D5: =Inputs!B8*D4 -> 72000
A6: Base loan amount (price - down) | B6: =Inputs!B8-B5 -> 347400 | C6: =Inputs!B8-C5 -> 342000 | D6: =Inputs!B8-D5 -> 288000
A7: Upfront MIP financed into loan (FHA only) | B7: =B6*Inputs!B18 -> 6079.5 | C7: =0 -> 0 | D7: =0 -> 0
A8: Total loan amount | B8: =B6+B7 -> 353479.5 | C8: =C6+C7 -> 342000 | D8: =D6+D7 -> 288000
A9: Term (months) | B9: =Inputs!B9*12 -> 360 | C9: =Inputs!B9*12 -> 360 | D9: =Inputs!B9*12 -> 360
A10: Monthly interest rate (r = annual / 12) | B10: =Inputs!B13/12 -> 0.0057291667 | C10: =Inputs!B13/12 -> 0.0057291667 | D10: =Inputs!B13/12 -> 0.0057291667
A11: Monthly P&I | B11: =-PMT(B10,B9,B8) -> 2322.1087 | C11: =-PMT(C10,C9,C8) -> 2246.6965 | D11: =-PMT(D10,D9,D8) -> 1891.955
A12: Monthly MI (PMI or MIP) — NEVER bundle into P&I | B12: =B8*Inputs!B19/12 -> 162.01144 | C12: =IF(C4<0.2,C8*Inputs!B21/12,0) -> 171 | D12: =IF(D4<0.2,D8*Inputs!B21/12,0) -> 0
A13: Monthly property tax (new-owner basis) | B13: ='PITI Build-Up'!B10 -> 374.58333 | C13: ='PITI Build-Up'!B10 -> 374.58333 | D13: ='PITI Build-Up'!B10 -> 374.58333
A14: Monthly HO3/HO6 insurance | B14: ='PITI Build-Up'!B14 -> 275 | C14: ='PITI Build-Up'!B14 -> 275 | D14: ='PITI Build-Up'!B14 -> 275
A15: Monthly HOA | B15: ='PITI Build-Up'!B17 -> 0 | C15: ='PITI Build-Up'!B17 -> 0 | D15: ='PITI Build-Up'!B17 -> 0
A16: TOTAL MONTHLY PITI | B16: =SUM(B11:B15) -> 3133.7035 | C16: =SUM(C11:C15) -> 3067.2799 | D16: =SUM(D11:D15) -> 2541.5383
A18: Front-end DTI (PITI / gross monthly) | B18: =IFERROR(B16/Inputs!B4,0) -> 0.40175685 | C18: =IFERROR(C16/Inputs!B4,0) -> 0.39324101 | D18: =IFERROR(D16/Inputs!B4,0) -> 0.32583825
A19: Back-end DTI ((PITI + debts) / gross monthly) | B19: =IFERROR((B16+Inputs!B5)/Inputs!B4,0) -> 0.48124403 | C19: =IFERROR((C16+Inputs!B5)/Inputs!B4,0) -> 0.47272819 | D19: =IFERROR((D16+Inputs!B5)/Inputs!B4,0) -> 0.40532543
A21: Notes:
A22: • Use the new-owner tax number, never the seller's last bill (Save-Our-Homes resets on sale).
A23: • MI is shown on its own line by design — never bundle it into P&I in any deliverable.
A24: • Conv 20% rows show $0 MI because LTV is 80%. If you switch Conv 20% to a different %, MI auto-applies.

Sheet Cash to Close
A1: Cash to Close | C1: What the prospect needs at closing — including the BAC line.
A3: Line item | B3: FHA 3.5% | C3: Conv 5% | D3: Conv 20%
A4: Down payment $ | B4: ='Loan Scenarios'!B5 -> 12600 | C4: ='Loan Scenarios'!C5 -> 18000 | D4: ='Loan Scenarios'!D5 -> 72000
A5: Lender fees (origination, underwriting, processing) | B5: =Inputs!B27 -> 2000 | C5: =Inputs!B27 -> 2000 | D5: =Inputs!B27 -> 2000
A6: Title (owner + lender policy + settlement) | B6: =Inputs!B28 -> 2750 | C6: =Inputs!B28 -> 2750 | D6: =Inputs!B28 -> 2750
A7: Recording + doc stamps + intangible tax (FL) | B7: =Inputs!B29 -> 1600 | C7: =Inputs!B29 -> 1600 | D7: =Inputs!B29 -> 1600
A8: Prepaids (1st-yr insurance, tax escrow, prepaid interest) | B8: =Inputs!B30 -> 2250 | C8: =Inputs!B30 -> 2250 | D8: =Inputs!B30 -> 2250
A9: Inspection + appraisal | B9: =Inputs!B31 -> 950 | C9: =Inputs!B31 -> 950 | D9: =Inputs!B31 -> 950
A10: Buyer agent compensation (buyer-paid portion) | B10: =Inputs!B32 -> 0 | C10: =Inputs!B32 -> 0 | D10: =Inputs!B32 -> 0
A11: TOTAL CASH TO CLOSE | B11: =SUM(B4:B10) -> 22150 | C11: =SUM(C4:C10) -> 27550 | D11: =SUM(D4:D10) -> 81550
A13: Notes:
A14: • Recording + doc stamps + intangible are NOT negotiable (Florida statute).
A15: • Lender fees, title, and prepaids ARE negotiable — seller credit is the lever.
A16: • BAC defaults to $0 = seller-paid. Set Inputs!B32 to the buyer-paid amount once the agreement is signed.

Sheet Reserves After Close
A1: Reserves After Close | C1: The single highest-impact number for a Tier A first-time buyer to see.
A3: Line item | B3: FHA 3.5% | C3: Conv 5% | D3: Conv 20%
A4: Cash available | B4: =Inputs!B7 -> 32000 | C4: =Inputs!B7 -> 32000 | D4: =Inputs!B7 -> 32000
A5: Cash to close | B5: ='Cash to Close'!B11 -> 22150 | C5: ='Cash to Close'!C11 -> 27550 | D5: ='Cash to Close'!D11 -> 81550
A6: Reserves $ remaining | B6: =B4-B5 -> 9850 | C6: =C4-C5 -> 4450 | D6: =D4-D5 -> -49550
A7: Monthly housing payment (PITI) | B7: ='Loan Scenarios'!B16 -> 3133.7035 | C7: ='Loan Scenarios'!C16 -> 3067.2799 | D7: ='Loan Scenarios'!D16 -> 2541.5383
A8: Reserves in MONTHS of housing | B8: =IFERROR(B6/B7,0) -> 3.1432457 | C8: =IFERROR(C6/C7,0) -> 1.4507969 | D8: =IFERROR(D6/D7,0) -> -19.496066
A9: Reserves flag | B9: =IF(B8<0,"RED — negative reserves",IF(B8<Inputs!$B$35,"RED — under "&TEXT(Inputs!$B$35,"0.0")&" mo",IF(B8<Inputs!$B$34,"YELLOW — under "&TEXT(Inputs!$B$34,"0.0")&" mo","OK"))) -> OK | C9: =IF(C8<0,"RED — negative reserves",IF(C8<Inputs!$B$35,"RED — under "&TEXT(Inputs!$B$35,"0.0")&" mo",IF(C8<Inputs!$B$34,"YELLOW — under "&TEXT(Inputs!$B$34,"0.0")&" mo","OK"))) -> OK | D9: =IF(D8<0,"RED — negative reserves",IF(D8<Inputs!$B$35,"RED — under "&TEXT(Inputs!$B$35,"0.0")&" mo",IF(D8<Inputs!$B$34,"YELLOW — under "&TEXT(Inputs!$B$34,"0.0")&" mo","OK"))) -> RED — negative reserves
A11: DTI CHECK
A12: Front-end DTI (PITI / gross) | B12: ='Loan Scenarios'!B18 -> 0.40175685 | C12: ='Loan Scenarios'!C18 -> 0.39324101 | D12: ='Loan Scenarios'!D18 -> 0.32583825
A13: Back-end DTI ((PITI + debts) / gross) | B13: ='Loan Scenarios'!B19 -> 0.48124403 | C13: ='Loan Scenarios'!C19 -> 0.47272819 | D13: ='Loan Scenarios'!D19 -> 0.40532543
A14: Back-end DTI flag | B14: =IF(B13>=Inputs!$B$37,"RED — over "&TEXT(Inputs!$B$37,"0%"),IF(B13>=Inputs!$B$36,"YELLOW — over "&TEXT(Inputs!$B$36,"0%"),"OK")) -> YELLOW — over 43% | C14: =IF(C13>=Inputs!$B$37,"RED — over "&TEXT(Inputs!$B$37,"0%"),IF(C13>=Inputs!$B$36,"YELLOW — over "&TEXT(Inputs!$B$36,"0%"),"OK")) -> YELLOW — over 43% | D14: =IF(D13>=Inputs!$B$37,"RED — over "&TEXT(Inputs!$B$37,"0%"),IF(D13>=Inputs!$B$36,"YELLOW — over "&TEXT(Inputs!$B$36,"0%"),"OK")) -> OK
A16: Reading this tab during the call:
A17: • Lead with row 8 (months of reserves). It answers 'will I be house-poor?'
A18: • Then row 13 (back-end DTI). If YELLOW or RED, the conversation shifts to lower price or longer prep timeline.
A19: • A scenario showing RED on either row is fine — the value is in showing what changes the picture.

Sheet Shortlist Math
A1: Shortlist Math — 3-Neighborhood Comparison | G1: One scenario applied across ZIPs. Toggle below.
A3: Loan scenario for comparison: | D3: 1 | E3: (1 = FHA 3.5%, 2 = Conv 5%, 3 = Conv 20%)
A5: Role | B5: Neighborhood / ZIP | C5: County | D5: Median price | E5: HOA/mo | F5: Down $ | G5: Total loan | H5: Monthly P&I | I5: Monthly MI | J5: Monthly tax | K5: Monthly ins | L5: TOTAL MONTHLY | M5: Gap vs prospect $/mo | N5: Cash to close | O5: Months to save gap
A6: PROSPECT | B6: =Inputs!B14 -> Sanford, maybe Lake Mary | C6: =Inputs!B11 -> Seminole | D6: =Inputs!B8 -> 360000 | E6: =Inputs!B12 -> 0 | F6: =D6*CHOOSE($D$3,Inputs!$B$17,Inputs!$B$20,Inputs!$B$22) -> 12600 | G6: =(D6-F6)*(1+CHOOSE($D$3,Inputs!$B$18,0,0)) -> 353479.5 | H6: =-PMT(Inputs!$B$13/12,Inputs!$B$9*12,G6) -> 2322.1087 | I6: =G6*CHOOSE($D$3,Inputs!$B$19,Inputs!$B$21,0)/12 -> 162.01144 | J6: =(MAX(0,D6-Inputs!$B$23)*IF(C6="Seminole",Inputs!$B$24,IF(C6="Orange",Inputs!$B$25,0)))/12 -> 374.58333 | K6: =Inputs!$B$26/12 -> 275 | L6: =H6+I6+J6+K6+E6 -> 3133.7035 | M6: =L6-$L$6 -> 0 | N6: =F6+SUM(Inputs!$B$27:$B$31)+Inputs!$B$32 -> 22150 | O6: =IFERROR(MAX(0,N6-$N$6)/Inputs!$B$33,0) -> 0
A7: ANCHOR | B7: Sanford 32771 | C7: Seminole | D7: 335000 | E7: 0 | F7: =D7*CHOOSE($D$3,Inputs!$B$17,Inputs!$B$20,Inputs!$B$22) -> 11725 | G7: =(D7-F7)*(1+CHOOSE($D$3,Inputs!$B$18,0,0)) -> 328932.31 | H7: =-PMT(Inputs!$B$13/12,Inputs!$B$9*12,G7) -> 2160.8511 | I7: =G7*CHOOSE($D$3,Inputs!$B$19,Inputs!$B$21,0)/12 -> 150.76064 | J7: =(MAX(0,D7-Inputs!$B$23)*IF(C7="Seminole",Inputs!$B$24,IF(C7="Orange",Inputs!$B$25,0)))/12 -> 344.375 | K7: =Inputs!$B$26/12 -> 275 | L7: =H7+I7+J7+K7+E7 -> 2930.9868 | M7: =L7-$L$6 -> -202.71668 | N7: =F7+SUM(Inputs!$B$27:$B$31)+Inputs!$B$32 -> 21275 | O7: =IFERROR(MAX(0,N7-$N$6)/Inputs!$B$33,0) -> 0
A8: STRETCH | B8: Maitland 32751 | C8: Orange | D8: 485000 | E8: 0 | F8: =D8*CHOOSE($D$3,Inputs!$B$17,Inputs!$B$20,Inputs!$B$22) -> 16975 | G8: =(D8-F8)*(1+CHOOSE($D$3,Inputs!$B$18,0,0)) -> 476215.44 | H8: =-PMT(Inputs!$B$13/12,Inputs!$B$9*12,G8) -> 3128.3964 | I8: =G8*CHOOSE($D$3,Inputs!$B$19,Inputs!$B$21,0)/12 -> 218.26541 | J8: =(MAX(0,D8-Inputs!$B$23)*IF(C8="Seminole",Inputs!$B$24,IF(C8="Orange",Inputs!$B$25,0)))/12 -> 489.375 | K8: =Inputs!$B$26/12 -> 275 | L8: =H8+I8+J8+K8+E8 -> 4111.0368 | M8: =L8-$L$6 -> 977.33338 | N8: =F8+SUM(Inputs!$B$27:$B$31)+Inputs!$B$32 -> 26525 | O8: =IFERROR(MAX(0,N8-$N$6)/Inputs!$B$33,0) -> 8.75
A9: WILDCARD | B9: Casselberry 32707 | C9: Seminole | D9: 315000 | E9: 0 | F9: =D9*CHOOSE($D$3,Inputs!$B$17,Inputs!$B$20,Inputs!$B$22) -> 11025 | G9: =(D9-F9)*(1+CHOOSE($D$3,Inputs!$B$18,0,0)) -> 309294.56 | H9: =-PMT(Inputs!$B$13/12,Inputs!$B$9*12,G9) -> 2031.8451 | I9: =G9*CHOOSE($D$3,Inputs!$B$19,Inputs!$B$21,0)/12 -> 141.76001 | J9: =(MAX(0,D9-Inputs!$B$23)*IF(C9="Seminole",Inputs!$B$24,IF(C9="Orange",Inputs!$B$25,0)))/12 -> 320.20833 | K9: =Inputs!$B$26/12 -> 275 | L9: =H9+I9+J9+K9+E9 -> 2768.8134 | M9: =L9-$L$6 -> -364.89002 | N9: =F9+SUM(Inputs!$B$27:$B$31)+Inputs!$B$32 -> 20575 | O9: =IFERROR(MAX(0,N9-$N$6)/Inputs!$B$33,0) -> 0
A10: OPTIONAL 4th | B10: (leave blank if not needed) | F10: =IF(ISNUMBER(D10),D10*CHOOSE($D$3,Inputs!$B$17,Inputs!$B$20,Inputs!$B$22),"") | G10: =IF(ISNUMBER(D10),(D10-F10)*(1+CHOOSE($D$3,Inputs!$B$18,0,0)),"") | H10: =IF(ISNUMBER(D10),-PMT(Inputs!$B$13/12,Inputs!$B$9*12,G10),"") | I10: =IF(ISNUMBER(D10),G10*CHOOSE($D$3,Inputs!$B$19,Inputs!$B$21,0)/12,"") | J10: =IF(ISNUMBER(D10),(MAX(0,D10-Inputs!$B$23)*IF(C10="Seminole",Inputs!$B$24,IF(C10="Orange",Inputs!$B$25,0)))/12,"") | K10: =IF(ISNUMBER(D10),Inputs!$B$26/12,"") | L10: =IF(ISNUMBER(D10),H10+I10+J10+K10+E10,"") | M10: =IF(ISNUMBER(D10),L10-$L$6,"") | N10: =IF(ISNUMBER(D10),F10+SUM(Inputs!$B$27:$B$31)+Inputs!$B$32,"") | O10: =IF(ISNUMBER(D10),IFERROR(MAX(0,N10-$N$6)/Inputs!$B$33,0),"")
A13: SHORTLIST DECISION LOGIC — Path A / B / C
A14: Path A — prospect had no neighborhoods in mind
A15: Agent picks: (1) Anchor — comfortable affordability, room for reserves. (2) Stretch — costs more but unlocks something specific (commute, schools, walkability). (3) Wildcard — they probably haven't considered it but it fits their numbers better than they'd guess.
A16: Path B — prospect named 1-2 ZIPs AND the math works
A17: Row 7 = their first named ZIP (math validated live). Row 8 = their second, or an adjacent agent-recommended ZIP. Row 9 = one agent-picked alternate, introduced explicitly. Prospect's preference always leads in the deliverable PDF.
A18: Path C — prospect named ZIPs AND the math doesn't work
A19: Row 7 = the named ZIP with the gap surfaced (NOT buried — show payment, reserves, DTI). Row 8 = the compromise inside the named ZIP (smaller home, older home, townhome instead of SFH, FHA instead of conv). Row 9 = the honest alternate — one ZIP outward, same product type, fits the math comfortably. The shortlist is never blank, and it never says 'you cannot afford this.'
A21: Hard rule: shortlist is 3 by default, 4 only in the cases listed in 12-bss-math-and-shortlist.md, NEVER 5.
